{
   "hidden" : 0,
   "navigation" : 1,
   "keywords" : null,
   "description" : "For maintainable and reusable code it is important to start with the right infrastructure choices and tools. In this chapter you will learn how to setup and design your project to achieve this.",
   "title" : "Example of a complete Rex code infrastructure",
   "url" : "example_of_a_complete_rex_code_infrastructure",
   "type_name" : "page",
   "content_type_name" : "text/html",
   "active" : 1,
   "name" : "Example of a complete Rex code infrastructure",
   "data" : {},
   "lock_date" : null
}
